api_client/__init__.py
api_client/authentication_methods.py
api_client/client.py
api_client/decorates.py
api_client/exceptions.py
api_client/request_formatters.py
api_client/response_handlers.py
api_client-0.1.0.dist-info/LICENSE
api_client-0.1.0.dist-info/METADATA
api_client-0.1.0.dist-info/WHEEL
api_client-0.1.0.dist-info/top_level.txt
api_client-0.1.0.dist-info/RECORD
