Metadata-Version: 2.1
Name: api-client
Version: 0.1.0
Summary: Separate the high level client implementation from the underlying CRUD operations.
Home-page: https://github.com/MikeWooster/api-client
Author: Mike Wooster
Author-email: 
License: UNKNOWN
Platform: UNKNOWN
Classifier: Development Status :: 2 - Pre-Alpha
Classifier: Programming Language :: Python :: 3.6
Classifier: License :: OSI Approved :: MIT License
Classifier: Operating System :: OS Independent
Classifier: Intended Audience :: Developers
Requires-Python: >=3.6
Requires-Dist: requests
Provides-Extra: dev
Requires-Dist: pytest ; extra == 'dev'
Requires-Dist: pytest-cov ; extra == 'dev'
Requires-Dist: vcrpy ; extra == 'dev'
Requires-Dist: flake8 ; extra == 'dev'
Requires-Dist: flake8-docstrings ; extra == 'dev'
Requires-Dist: black ; extra == 'dev'
Requires-Dist: ipdb ; extra == 'dev'
Provides-Extra: docs
Requires-Dist: pytest ; extra == 'docs'
Requires-Dist: pytest-cov ; extra == 'docs'
Requires-Dist: vcrpy ; extra == 'docs'
Requires-Dist: flake8 ; extra == 'docs'
Requires-Dist: flake8-docstrings ; extra == 'docs'
Requires-Dist: black ; extra == 'docs'
Requires-Dist: ipdb ; extra == 'docs'
Provides-Extra: lint
Requires-Dist: flake8 ; extra == 'lint'
Requires-Dist: flake8-docstrings ; extra == 'lint'
Requires-Dist: black ; extra == 'lint'
Provides-Extra: production
Provides-Extra: test
Requires-Dist: pytest ; extra == 'test'
Requires-Dist: pytest-cov ; extra == 'test'
Requires-Dist: vcrpy ; extra == 'test'
